link2media/__init__.py
link2media/audio_download.py
link2media/count_core.py
link2media/quality_audio.py
link2media/video_download.py
link2media-1.1.2.dist-info/METADATA
link2media-1.1.2.dist-info/WHEEL
link2media-1.1.2.dist-info/top_level.txt
link2media-1.1.2.dist-info/RECORD
