Metadata-Version: 2.1
Name: link2media
Version: 1.1.2
Author: tawsif
Author-email: sleeping4cat@outlook.com
Requires-Dist: pytube
Requires-Dist: ffmpeg-python
